slackbot_helper/__init__.py
slackbot_helper/blocks/__init__.py
slackbot_helper/blocks/bp/__init__.py
slackbot_helper/blocks/bp/result_block.py
slackbot_helper/blocks/dmo/__init__.py
slackbot_helper/blocks/dmo/book_only_block.py
slackbot_helper/blocks/dmo/chapter_and_page_block.py
slackbot_helper/blocks/dmo/standard_text_block.py
slackbot_helper/blocks/dto/__init__.py
slackbot_helper/blocks/dto/book_emojis_kb.py
slackbot_helper/blocks/svc/__init__.py
slackbot_helper/core/__init__.py
slackbot_helper/core/bp/__init__.py
slackbot_helper/core/bp/normalize_incoming_event.py
slackbot_helper/core/dmo/__init__.py
slackbot_helper/core/dmo/exact_match_highlighter.py
slackbot_helper/core/dmo/fuzzy_match_highlighter.py
slackbot_helper/core/dmo/message_text_extract.py
slackbot_helper/core/dmo/message_type_analysis.py
slackbot_helper/core/dmo/user_id_extract.py
slackbot_helper/core/dto/__init__.py
slackbot_helper/core/dto/message_type.py
slackbot_helper/core/dto/typedefs.py
slackbot_helper/core/svc/__init__.py
slackbot_helper/core/svc/analyze_slack_event.py
slackbot_helper/core/svc/highlight_output_text.py
slackbot_helper/core/svc/transform_incoming_event.py
slackbot_helper-0.1.42.dist-info/WHEEL
slackbot_helper-0.1.42.dist-info/METADATA
slackbot_helper-0.1.42.dist-info/RECORD
