Metadata-Version: 2.1
Name: slackbot-helper
Version: 0.1.42
Summary: Helper Functions for Slackbots
Home-page: https://github.com/craigtrim/slackbot-helper
License: MIT
Keywords: chatbot,bot,slack,helper,utility
Author: Craig Trim
Author-email: craigtrim@gmail.com
Maintainer: Craig Trim
Maintainer-email: craigtrim@gmail.com
Requires-Python: >=3.8.5,<4.0.0
Classifier: Development Status :: 4 - Beta
Classifier: License :: OSI Approved :: MIT License
Classifier: Programming Language :: Python :: 3
Classifier: Programming Language :: Python :: 3.10
Classifier: Programming Language :: Python :: 3.9
Classifier: Topic :: Software Development :: Libraries :: Python Modules
Requires-Dist: baseblock
Requires-Dist: fast_sentence_tokenize
Requires-Dist: slack-bolt (>=1.14.3,<2.0.0)
Requires-Dist: slackclient (>=2.9.4,<3.0.0)
Project-URL: Bug Tracker, https://github.com/craigtrim/slackbot-helper/issues
Project-URL: Repository, https://github.com/craigtrim/slackbot-helper
